mlwiz/__init__.py
mlwiz/build_dataset.py
mlwiz/config_duplicator.py
mlwiz/exceptions.py
mlwiz/launch_experiment.py
mlwiz/static.py
mlwiz/util.py
mlwiz/data/__init__.py
mlwiz/data/dataset.py
mlwiz/data/provider.py
mlwiz/data/sampler.py
mlwiz/data/splitter.py
mlwiz/data/util.py
mlwiz/evaluation/__init__.py
mlwiz/evaluation/config.py
mlwiz/evaluation/evaluator.py
mlwiz/evaluation/grid.py
mlwiz/evaluation/random_search.py
mlwiz/evaluation/util.py
mlwiz/experiment/__init__.py
mlwiz/experiment/experiment.py
mlwiz/log/__init__.py
mlwiz/log/logger.py
mlwiz/model/__init__.py
mlwiz/model/graph.py
mlwiz/model/interface.py
mlwiz/model/timeseries.py
mlwiz/model/vector.py
mlwiz/training/__init__.py
mlwiz/training/engine.py
mlwiz/training/profiler.py
mlwiz/training/util.py
mlwiz/training/callback/__init__.py
mlwiz/training/callback/early_stopping.py
mlwiz/training/callback/engine_callback.py
mlwiz/training/callback/gradient_clipping.py
mlwiz/training/callback/metric.py
mlwiz/training/callback/optimizer.py
mlwiz/training/callback/plotter.py
mlwiz/training/callback/scheduler.py
mlwiz/training/event/__init__.py
mlwiz/training/event/dispatcher.py
mlwiz/training/event/handler.py
mlwiz/training/event/state.py
mlwiz-1.4.0.dist-info/licenses/LICENSE
mlwiz-1.4.0.dist-info/METADATA
mlwiz-1.4.0.dist-info/WHEEL
mlwiz-1.4.0.dist-info/entry_points.txt
mlwiz-1.4.0.dist-info/top_level.txt
mlwiz-1.4.0.dist-info/RECORD
