Metadata-Version: 2.4
Name: mlwiz
Version: 1.4.0
Summary: Machine Learning Research Wizard
Author-email: Federico Errica <f.errica@protonmail.com>
Project-URL: Homepage, https://mlwiz.readthedocs.io/en/latest/
Keywords: machine-learning,deep-learning,experiments,research,evaluation-framework
Classifier: Programming Language :: Python :: 3
Classifier: License :: OSI Approved :: BSD License
Classifier: Operating System :: POSIX :: Linux
Requires-Python: >=3.10
License-File: LICENSE
Requires-Dist: PyYAML>=5.4
Requires-Dist: dill>=0.3.8
Requires-Dist: Requests>=2.31.0
Requires-Dist: scikit_learn>=1.3.0
Requires-Dist: scipy>=1.15.3
Requires-Dist: pandas>=2.0.0
Requires-Dist: tensorboard>=2.11.0
Requires-Dist: tqdm>=4.47.0
Requires-Dist: ray[default]>=2.6.0
Requires-Dist: torchvision>=0.18.1
Requires-Dist: torch>=2.5.0
Requires-Dist: torch-geometric>=2.6.0
Requires-Dist: gpustat
Dynamic: license-file
